[{"email":"rose@yahoo.com","password":"newnew"},{"email":"info@jidetaiwoandco.com","password":"password1"},{"email":"rose@yahoo.com","password":"hdhdd"},{"email":"rose@yahoo.com","password":"hdhdd"},{"email":"info@jidetaiwoandco.com","password":"bagafss"},{"email":"john@yahoo.com","password":"kldsfdf"},{"email":"john@yahoo.com","password":"kldsfdf"},{"email":"john@yahoo.com","password":"kldsfdf"},{"email":"john@yahoo.com","password":"kjlsdlsd"},{"email":"john@yahoo.com","password":"kjlsdlsd"},{"email":"john@yahoo.com","password":"kjlsdlsd"},{"email":"john@yahoo.com","password":"kjlsdlsd"},{"email":"john@yahoo.com","password":"kfldkfldf"},{"email":"john@yahoo.com","password":"kfldkfldf"},{"email":"john@yahoo.com","password":"kfldkfldf"},{"email":"john@yahoo.com","password":"kfldkfldf"},{"email":"john@yahoo.com","password":"kfldkfldf"},{"email":"john@yahoo.com","password":"kfldkfldf"},{"email":"john@yahoo.com","password":"kfldkfldf"},{"email":"john@yahoo.com","password":"kfldkfldf"},{"email":"john@yahoo.com","password":"kfldkfldf"},{"email":"john@yahoo.com","password":"kfldkfldf"},{"email":"john@yahoo.com","password":"kfldkfldf"},{"email":"john@yahoo.com","password":"kfldkfldf"},{"email":"john@yahoo.com","password":"kfldkfldf"},{"email":"john@yahoo.com","password":"kfldkfldf"},{"email":"john@yahoo.com","password":"kjlsdlsd"},{"email":"john@yahoo.com","password":"kjlsdlsd"},{"email":"daviduwana@gmail.com","password":"asdfgh"},{"email":"daviduwana@gmail.com","password":"asdfgh"},{"email":"daviduwana@gmail.com","password":"abcdefgh"},{"email":"daviduwana@gmail.com","password":"asdfghjk"},{"email":"daviduwana@gmail.com","password":"aaaaaaaaa"},{"email":"lewebber007@gmail.com","password":"fffffffff"},{"email":"theshogunofnetworks@protonmail.com","password":"yuyuyu"},{"email":"theshogunofnetworks@protonmail.com","password":"yyyy"},{"email":"theshogunofnetworks@protonmail.com","password":"ddddd"},{"email":"daviduwana@gmail.com","password":"bbbb"}]